koscrap/__init__.py
koscrap/coupang.py
koscrap/namuwiki.py
koscrap/wikipedia.py
koscrap/modules/__init__.py
koscrap/modules/get_soup.py
koscrap/tests/__init__.py
koscrap/tests/test_coupang.py
koscrap/tests/test_wikipedia.py
scrpy/__init__.py
scrpy/namuwiki.py
scrpy/scraper.py
scrpy/wikipedia.py
scrpy/modules/__init__.py
scrpy/modules/get_soup.py
scrpy/tests/__init__.py
scrpy/tests/test_wikipedia.py
web_scraper/__init__.py
web_scraper/namuwiki.py
web_scraper/scraper.py
web_scraper/wikipedia.py
web_scraper/modules/__init__.py
web_scraper/modules/get_soup.py
web_scraper/tests/__init__.py
web_scraper/tests/test_wikipedia.py
wecrap/__init__.py
wecrap/namuwiki.py
wecrap/scraper.py
wecrap/wikipedia.py
wecrap/modules/__init__.py
wecrap/modules/get_soup.py
wecrap/tests/__init__.py
wecrap/tests/test_wikipedia.py
koscrap-1.1.0.dist-info/METADATA
koscrap-1.1.0.dist-info/WHEEL
koscrap-1.1.0.dist-info/top_level.txt
koscrap-1.1.0.dist-info/RECORD
